ms_recognizers_number_with_unit/__init__.py
ms_recognizers_number_with_unit/number_with_unit/__init__.py
ms_recognizers_number_with_unit/number_with_unit/constants.py
ms_recognizers_number_with_unit/number_with_unit/extractors.py
ms_recognizers_number_with_unit/number_with_unit/models.py
ms_recognizers_number_with_unit/number_with_unit/number_with_unit_recognizer.py
ms_recognizers_number_with_unit/number_with_unit/parsers.py
ms_recognizers_number_with_unit/number_with_unit/utilities.py
ms_recognizers_number_with_unit/number_with_unit/chinese/__init__.py
ms_recognizers_number_with_unit/number_with_unit/chinese/extractors.py
ms_recognizers_number_with_unit/number_with_unit/chinese/parsers.py
ms_recognizers_number_with_unit/number_with_unit/dutch/__init__.py
ms_recognizers_number_with_unit/number_with_unit/dutch/extractors.py
ms_recognizers_number_with_unit/number_with_unit/dutch/parsers.py
ms_recognizers_number_with_unit/number_with_unit/english/__init__.py
ms_recognizers_number_with_unit/number_with_unit/english/extractors.py
ms_recognizers_number_with_unit/number_with_unit/english/parsers.py
ms_recognizers_number_with_unit/number_with_unit/french/__init__.py
ms_recognizers_number_with_unit/number_with_unit/french/extractors.py
ms_recognizers_number_with_unit/number_with_unit/french/parsers.py
ms_recognizers_number_with_unit/number_with_unit/german/__init__.py
ms_recognizers_number_with_unit/number_with_unit/german/extractors.py
ms_recognizers_number_with_unit/number_with_unit/german/parsers.py
ms_recognizers_number_with_unit/number_with_unit/italian/__init__.py
ms_recognizers_number_with_unit/number_with_unit/italian/extractors.py
ms_recognizers_number_with_unit/number_with_unit/italian/parsers.py
ms_recognizers_number_with_unit/number_with_unit/portuguese/__init__.py
ms_recognizers_number_with_unit/number_with_unit/portuguese/extractors.py
ms_recognizers_number_with_unit/number_with_unit/portuguese/parsers.py
ms_recognizers_text_number_with_unit-1.0.0.1.dist-info/METADATA
ms_recognizers_text_number_with_unit-1.0.0.1.dist-info/WHEEL
ms_recognizers_text_number_with_unit-1.0.0.1.dist-info/top_level.txt
ms_recognizers_text_number_with_unit-1.0.0.1.dist-info/RECORD
